  [
    {
      "name":"Chandra Prakash",
      "email":"chandu2013pal@gmail.com",
      "mobile":"9818268558",
      "message":"Hello,i am chandra prakash pal"
    },
    {
      "name":"Prakash",
      "email":"prakash@123gmail.com",
      "mobile":"093834734344",
      "message":"Hello,i am chandra prakash pal"
    },
    {
      "name":"Friend",
      "email":"Abc",
      "mobile":"Abc",
      "message":"sdsssadas dsdf"
    },
    {
      "name":"Friend",
      "email":"Abc",
      "mobile":"Abc",
      "message":"sdsssadas dsdf"
    },
    {
      "name":"Friend",
      "email":"Abc",
      "mobile":"Abc",
      "message":"sdsssadas dsdf"
    }
  ]
